score.serve-0.1.27-py3.11-nspkg.pth
score/serve/__init__.py
score/serve/_changedetect.py
score/serve/_forked.py
score/serve/_init.py
score/serve/cli.py
score/serve/monitor.py
score/serve/service.py
score/serve/worker/__init__.py
score/serve/worker/asyncio.py
score/serve/worker/simple.py
score/serve/worker/socketserver.py
score/serve/worker/watcher.py
score/serve/worker/worker.py
score.serve-0.1.27.dist-info/COPYING.LESSER.txt
score.serve-0.1.27.dist-info/METADATA
score.serve-0.1.27.dist-info/WHEEL
score.serve-0.1.27.dist-info/entry_points.txt
score.serve-0.1.27.dist-info/namespace_packages.txt
score.serve-0.1.27.dist-info/top_level.txt
score.serve-0.1.27.dist-info/RECORD
